{
    "fertilizer": {
        "composition": {
            "N": 0.0,
            "P": 0.0,
            "K": 0.0
        },
        "rotation_years": [2009],
        "repeat": 1,
        "year": [],
        "day": [],
        "N_mass": [],
        "P_mass": [],
        "K_mass": [],
        "depth": [],
        "surface_percent": []
    },
    "manure": {
        "rotation_years": [2009],
        "repeat": 1,
        "year": [2009, 2010, 2011, 2012, 2013, 2014, 2015, 2016],
        "day": [120, 120, 120, 120, 120, 120, 120, 120],
        "N_mass": [10000, 10000, 10000, 10000, 10000, 10000, 10000, 10000],
        "P_mass": [0, 0, 0, 0, 0, 0, 0, 0],
        "cover_percent": [0.95, 0.95, 0.95, 0.95, 0.95, 0.95, 0.95, 0.95],
        "depth": [0.0, 0.0, 0.0, 0.0, 0.0, 0.0, 0.0, 0.0],
        "surface_percent": [1.0, 1.0, 1.0, 1.0, 1.0, 1.0, 1.0, 1.0]
    },
    "tillage": {
        "rotation_years": [],
        "repeat": 0,
        "year": [],
        "day": [],
        "perc_incorporated": [],
        "perc_mixed": [],
        "depth": []
    }
}