{
  "title": "economic_properties",
  "type": "object",
  "format": "grid",
  "properties": {
    "diesel_cost_gal": {
      "title": "diesel_cost_gal",
      "type": "number",
      "options": {
        "grid_columns": 12,
        "inputAttributes": {
          "class": "text-primary form-control"
        },
        "infoText": "cost of diesel per gallon"
      },
      "minimum": 0,
      "default": 5.0
    },
    "electricity_cost_kwh": {
      "title": "electricity_cost_kwh",
      "type": "number",
      "options": {
        "grid_columns": 12,
        "inputAttributes": {
          "class": "text-primary form-control"
        },
        "infoText": "cost of electricity per kwh"
      },
      "minimum": 0,
      "default": 0.15
    },
    "natural_gas_cost_kwh": {
      "title": "natural_gas_cost_kwh",
      "type": "number",
      "options": {
        "grid_columns": 12,
        "inputAttributes": {
          "class": "text-primary form-control"
        },
        "infoText": "cost of natural gas per kwh"
      },
      "minimum": 0,
      "default": 0.053
    },
    "water_cost_gal": {
      "title": "water_cost_gal",
      "type": "number",
      "options": {
        "grid_columns": 12,
        "inputAttributes": {
          "class": "text-primary form-control"
        },
        "infoText": "cost of water per gallon"
      },
      "minimum": 0,
      "default": 0.008
    }
  }
}